milalliancetaxes/__init__.py
milalliancetaxes/admin.py
milalliancetaxes/app_settings.py
milalliancetaxes/apps.py
milalliancetaxes/auth_hooks.py
milalliancetaxes/providers.py
milalliancetaxes/signals.py
milalliancetaxes/tasks.py
milalliancetaxes/tests.py
milalliancetaxes/urls.py
milalliancetaxes/views.py
milalliancetaxes/dataclasses/wallet_ledger.py
milalliancetaxes/migrations/0001_initial.py
milalliancetaxes/migrations/0002_corporation_tax_rate.py
milalliancetaxes/migrations/__init__.py
milalliancetaxes/models/__init__.py
milalliancetaxes/models/corp_ceo.py
milalliancetaxes/models/corporation.py
milalliancetaxes/models/general.py
milalliancetaxes/models/tax_ledger.py
milalliancetaxes/templates/milalliancetaxes/admin_panel.html
milalliancetaxes/templates/milalliancetaxes/base.html
milalliancetaxes/templates/milalliancetaxes/invalid_date.html
milalliancetaxes/templates/milalliancetaxes/tax_overview.html
mil_alliance_taxes-1.0.7.dist-info/licenses/LICENSE
mil_alliance_taxes-1.0.7.dist-info/WHEEL
mil_alliance_taxes-1.0.7.dist-info/METADATA
mil_alliance_taxes-1.0.7.dist-info/RECORD
